s_interpreter/__init__.py
s_interpreter/compiler.py
s_interpreter/interpreter.py
s_interpreter-1.0.0.dist-info/LICENSE
s_interpreter-1.0.0.dist-info/METADATA
s_interpreter-1.0.0.dist-info/WHEEL
s_interpreter-1.0.0.dist-info/entry_points.txt
s_interpreter-1.0.0.dist-info/top_level.txt
s_interpreter-1.0.0.dist-info/RECORD
