Metadata-Version: 2.1
Name: s-interpreter
Version: 1.0.0
Summary: A package for compiling and interpreting S Language code
Author-email: Muli Silman <mulisilman@gmail.com>
Project-URL: Homepage, https://github.com/SamuelSill/s_interpreter
Project-URL: Bug Tracker, https://github.com/SamuelSill/s_interpreter/issues
Classifier: Programming Language :: Python :: 3
Classifier: License :: OSI Approved :: MIT License
Classifier: Operating System :: OS Independent
Requires-Python: >=3.9
License-File: LICENSE
Requires-Dist: sympy (>=1.11.1)
